criminal_export_utils/__init__.py
criminal_export_utils/export_utils.py
criminal_export_utils-0.1.0.dist-info/licenses/LICENSE
criminal_export_utils-0.1.0.dist-info/METADATA
criminal_export_utils-0.1.0.dist-info/WHEEL
criminal_export_utils-0.1.0.dist-info/top_level.txt
criminal_export_utils-0.1.0.dist-info/RECORD
