Metadata-Version: 2.4
Name: criminal-export-utils
Version: 0.1.0
Summary: Utility library for exporting data to Excel and CSV files
Author-email: ValRudyka <val.rudika@gmail.com>
License-Expression: MIT
Project-URL: Homepage, https://github.com/ValRudyka/pypi-example
Requires-Python: >=3.8
License-File: LICENSE
Requires-Dist: openpyxl>=3.0.0
Requires-Dist: PySide6>=6.0.0
Dynamic: license-file
